<?xml version="1.0"?>
<GameState xmlns:xsd="http://www.w3.org/2001/XMLSchema" xmlns:xsi="http://www.w3.org/2001/XMLSchema-instance">
  <robotStates>
    <RobotState>
      <position>
        <x>114.805176</x>
        <y>0.101764947</y>
        <z>772.8974</z>
      </position>
      <rotation>
        <x>-0</x>
        <y>-0.5338618</y>
        <z>-0</z>
        <w>-0.8455718</w>
        <eulerAngles>
          <x>-0</x>
          <y>64.53351</y>
          <z>0</z>
        </eulerAngles>
      </rotation>
      <health>100</health>
      <state>Idle</state>
    </RobotState>
    <RobotState>
      <position>
        <x>135.564072</x>
        <y>0.0609674454</y>
        <z>244.780792</z>
      </position>
      <rotation>
        <x>-0</x>
        <y>0.6937217</y>
        <z>-0</z>
        <w>-0.720243156</w>
        <eulerAngles>
          <x>0</x>
          <y>272.1491</y>
          <z>0</z>
        </eulerAngles>
      </rotation>
      <health>100</health>
      <state>Patrolling</state>
    </RobotState>
    <RobotState>
      <position>
        <x>106.70517</x>
        <y>0.141367972</y>
        <z>761.8974</z>
      </position>
      <rotation>
        <x>-0</x>
        <y>-0.5338618</y>
        <z>-0</z>
        <w>-0.8455718</w>
        <eulerAngles>
          <x>-0</x>
          <y>64.53351</y>
          <z>0</z>
        </eulerAngles>
      </rotation>
      <health>100</health>
      <state>Idle</state>
    </RobotState>
    <RobotState>
      <position>
        <x>298.245728</x>
        <y>0.0609674454</y>
        <z>935.9147</z>
      </position>
      <rotation>
        <x>-0</x>
        <y>0.751085</y>
        <z>-0</z>
        <w>-0.6602056</w>
        <eulerAngles>
          <x>0</x>
          <y>262.6311</y>
          <z>0</z>
        </eulerAngles>
      </rotation>
      <health>100</health>
      <state>Patrolling</state>
    </RobotState>
    <RobotState>
      <position>
        <x>354.674622</x>
        <y>0.153972208</y>
        <z>630.7015</z>
      </position>
      <rotation>
        <x>-0</x>
        <y>-0.403562754</y>
        <z>-0</z>
        <w>0.91495204</w>
        <eulerAngles>
          <x>-0</x>
          <y>312.397827</y>
          <z>0</z>
        </eulerAngles>
      </rotation>
      <health>100</health>
      <state>Patrolling</state>
    </RobotState>
    <RobotState>
      <position>
        <x>122.70517</x>
        <y>0.213829368</y>
        <z>756.3974</z>
      </position>
      <rotation>
        <x>-0</x>
        <y>-0.5338618</y>
        <z>-0</z>
        <w>-0.8455718</w>
        <eulerAngles>
          <x>-0</x>
          <y>64.53351</y>
          <z>0</z>
        </eulerAngles>
      </rotation>
      <health>100</health>
      <state>Idle</state>
    </RobotState>
    <RobotState>
      <position>
        <x>302.1704</x>
        <y>0.0609674454</y>
        <z>906.6763</z>
      </position>
      <rotation>
        <x>-0</x>
        <y>0.751085</y>
        <z>-0</z>
        <w>-0.6602056</w>
        <eulerAngles>
          <x>0</x>
          <y>262.6311</y>
          <z>0</z>
        </eulerAngles>
      </rotation>
      <health>100</health>
      <state>Patrolling</state>
    </RobotState>
    <RobotState>
      <position>
        <x>170.334045</x>
        <y>0.0609674454</y>
        <z>240.94</z>
      </position>
      <rotation>
        <x>-0</x>
        <y>-0.991834641</y>
        <z>-0</z>
        <w>0.127530381</w>
        <eulerAngles>
          <x>-0</x>
          <y>194.653809</y>
          <z>0</z>
        </eulerAngles>
      </rotation>
      <health>100</health>
      <state>Patrolling</state>
    </RobotState>
    <RobotState>
      <position>
        <x>304.4704</x>
        <y>0.0609674454</y>
        <z>889.276245</z>
      </position>
      <rotation>
        <x>-0</x>
        <y>0.751085</y>
        <z>-0</z>
        <w>-0.6602056</w>
        <eulerAngles>
          <x>0</x>
          <y>262.6311</y>
          <z>0</z>
        </eulerAngles>
      </rotation>
      <health>100</health>
      <state>Patrolling</state>
    </RobotState>
    <RobotState>
      <position>
        <x>87.0933456</x>
        <y>0.109957583</y>
        <z>457.8521</z>
      </position>
      <rotation>
        <x>-0</x>
        <y>-0.2264337</y>
        <z>-0</z>
        <w>-0.9740266</w>
        <eulerAngles>
          <x>-0</x>
          <y>26.1743965</y>
          <z>0</z>
        </eulerAngles>
      </rotation>
      <health>100</health>
      <state>Idle</state>
    </RobotState>
    <RobotState>
      <position>
        <x>300.1704</x>
        <y>0.0609674454</y>
        <z>921.6763</z>
      </position>
      <rotation>
        <x>-0</x>
        <y>0.751085</y>
        <z>-0</z>
        <w>-0.6602056</w>
        <eulerAngles>
          <x>0</x>
          <y>262.6311</y>
          <z>0</z>
        </eulerAngles>
      </rotation>
      <health>100</health>
      <state>Patrolling</state>
    </RobotState>
    <RobotState>
      <position>
        <x>128.126709</x>
        <y>0.284267277</y>
        <z>744.9359</z>
      </position>
      <rotation>
        <x>-0</x>
        <y>-0.5338618</y>
        <z>-0</z>
        <w>-0.8455718</w>
        <eulerAngles>
          <x>-0</x>
          <y>64.53351</y>
          <z>0</z>
        </eulerAngles>
      </rotation>
      <health>100</health>
      <state>Idle</state>
    </RobotState>
    <RobotState>
      <position>
        <x>113.805176</x>
        <y>0.336355627</y>
        <z>747.097351</z>
      </position>
      <rotation>
        <x>-0</x>
        <y>-0.5338618</y>
        <z>-0</z>
        <w>-0.8455718</w>
        <eulerAngles>
          <x>-0</x>
          <y>64.53351</y>
          <z>0</z>
        </eulerAngles>
      </rotation>
      <health>100</health>
      <state>Idle</state>
    </RobotState>
    <RobotState>
      <position>
        <x>394.210632</x>
        <y>0.207445949</y>
        <z>618.2942</z>
      </position>
      <rotation>
        <x>-0</x>
        <y>-0.868959</y>
        <z>-0</z>
        <w>-0.494884223</w>
        <eulerAngles>
          <x>-0</x>
          <y>120.675774</y>
          <z>0</z>
        </eulerAngles>
      </rotation>
      <health>100</health>
      <state>Patrolling</state>
    </RobotState>
    <RobotState>
      <position>
        <x>260.859436</x>
        <y>0.161988586</y>
        <z>574.640137</z>
      </position>
      <rotation>
        <x>-0</x>
        <y>-0.8020256</y>
        <z>-0</z>
        <w>0.597289741</w>
        <eulerAngles>
          <x>-0</x>
          <y>253.352066</y>
          <z>0</z>
        </eulerAngles>
      </rotation>
      <health>100</health>
      <state>Patrolling</state>
    </RobotState>
    <RobotState>
      <position>
        <x>374.29245</x>
        <y>0.0662085</y>
        <z>582.1417</z>
      </position>
      <rotation>
        <x>-0</x>
        <y>0.6940834</y>
        <z>-0</z>
        <w>0.719894648</w>
        <eulerAngles>
          <x>-0</x>
          <y>87.90843</y>
          <z>-0</z>
        </eulerAngles>
      </rotation>
      <health>100</health>
      <state>Patrolling</state>
    </RobotState>
    <RobotState>
      <position>
        <x>381.1276</x>
        <y>0.227633953</y>
        <z>660.4431</z>
      </position>
      <rotation>
        <x>-0</x>
        <y>0.758683443</y>
        <z>-0</z>
        <w>-0.6514594</w>
        <eulerAngles>
          <x>0</x>
          <y>261.303467</y>
          <z>0</z>
        </eulerAngles>
      </rotation>
      <health>100</health>
      <state>Patrolling</state>
    </RobotState>
  </robotStates>
  <playerState>
    <position>
      <x>183.657852</x>
      <y>5.38848352</y>
      <z>556.4034</z>
    </position>
    <rotation>
      <x>0</x>
      <y>0.5657248</y>
      <z>0</z>
      <w>0.82459414</w>
      <eulerAngles>
        <x>-0</x>
        <y>68.90527</y>
        <z>0</z>
      </eulerAngles>
    </rotation>
    <health>100</health>
    <score>700</score>
  </playerState>
  <level>2</level>
</GameState>